<?xml version='1.0' encoding='UTF-8'?>
<history>
   <processor signature="gcc -shared -lm -lpthread -ldl -lstdc++">
      <target file="libjatanor.so" lastModified="162cdd27e78">
         <source file="../../../objs/linux/atanor.o" lastModified="162cdc13898"/>
         <source file="../../../objs/linux/atanoratanor.o" lastModified="162cdc14450"/>
         <source file="../../../objs/linux/atanorbinmap.o" lastModified="162cdc1f418"/>
         <source file="../../../objs/linux/atanorbinmapf.o" lastModified="162cdc20f70"/>
         <source file="../../../objs/linux/atanorbinmapi.o" lastModified="162cdc1ffd0"/>
         <source file="../../../objs/linux/atanorbinmapl.o" lastModified="162cdc7e788"/>
         <source file="../../../objs/linux/atanorbinmaps.o" lastModified="162cdc21f10"/>
         <source file="../../../objs/linux/atanorbinmapu.o" lastModified="162cdc22ac8"/>
         <source file="../../../objs/linux/atanorbool.o" lastModified="162cdc14c20"/>
         <source file="../../../objs/linux/atanorbvector.o" lastModified="162cdc15bc0"/>
         <source file="../../../objs/linux/atanorbyte.o" lastModified="162cdc16390"/>
         <source file="../../../objs/linux/atanordate.o" lastModified="162cdc16f48"/>
         <source file="../../../objs/linux/atanordecimal.o" lastModified="162cdc17ee8"/>
         <source file="../../../objs/linux/atanordvector.o" lastModified="162cdc1e478"/>
         <source file="../../../objs/linux/atanorfile.o" lastModified="162cdc186b8"/>
         <source file="../../../objs/linux/atanorfloat.o" lastModified="162cdc19e28"/>
         <source file="../../../objs/linux/atanorfmatrix.o" lastModified="162cdc1a9e0"/>
         <source file="../../../objs/linux/atanorfraction.o" lastModified="162cdc1b1b0"/>
         <source file="../../../objs/linux/atanorframeinstance.o" lastModified="162cdc1bd68"/>
         <source file="../../../objs/linux/atanorfvector.o" lastModified="162cdc1d0f0"/>
         <source file="../../../objs/linux/atanorgrammar.o" lastModified="162cdc25d90"/>
         <source file="../../../objs/linux/atanorhaskell.o" lastModified="162cdc27118"/>
         <source file="../../../objs/linux/atanorhvector.o" lastModified="162cdc7d7e8"/>
         <source file="../../../objs/linux/atanorimatrix.o" lastModified="162cdc27cd0"/>
         <source file="../../../objs/linux/atanorint.o" lastModified="162cdc28888"/>
         <source file="../../../objs/linux/atanoriterator.o" lastModified="162cdc29058"/>
         <source file="../../../objs/linux/atanorivector.o" lastModified="162cdc2a3e0"/>
         <source file="../../../objs/linux/atanorlist.o" lastModified="162cdc2b380"/>
         <source file="../../../objs/linux/atanorlong.o" lastModified="162cdc2d2c0"/>
         <source file="../../../objs/linux/atanorlvector.o" lastModified="162cdc2c708"/>
         <source file="../../../objs/linux/atanormap.o" lastModified="162cdc2e260"/>
         <source file="../../../objs/linux/atanormapf.o" lastModified="162cdc2ee18"/>
         <source file="../../../objs/linux/atanormapff.o" lastModified="162cdc2f9d0"/>
         <source file="../../../objs/linux/atanormapfi.o" lastModified="162cdc30588"/>
         <source file="../../../objs/linux/atanormapfl.o" lastModified="162cdc7f340"/>
         <source file="../../../objs/linux/atanormapfs.o" lastModified="162cdc31140"/>
         <source file="../../../objs/linux/atanormapfu.o" lastModified="162cdc320e0"/>
         <source file="../../../objs/linux/atanormapi.o" lastModified="162cdc32c98"/>
         <source file="../../../objs/linux/atanormapif.o" lastModified="162cdc33850"/>
         <source file="../../../objs/linux/atanormapii.o" lastModified="162cdc34408"/>
         <source file="../../../objs/linux/atanormapis.o" lastModified="162cdc34fc0"/>
         <source file="../../../objs/linux/atanormapiu.o" lastModified="162cdc35f60"/>
         <source file="../../../objs/linux/atanormapl.o" lastModified="162cdc7fef8"/>
         <source file="../../../objs/linux/atanormaplf.o" lastModified="162cdc80e98"/>
         <source file="../../../objs/linux/atanormapll.o" lastModified="162cdc81a50"/>
         <source file="../../../objs/linux/atanormapls.o" lastModified="162cdc82608"/>
         <source file="../../../objs/linux/atanormaplu.o" lastModified="162cdc835a8"/>
         <source file="../../../objs/linux/atanormapsf.o" lastModified="162cdc36b18"/>
         <source file="../../../objs/linux/atanormapsi.o" lastModified="162cdc376d0"/>
         <source file="../../../objs/linux/atanormapsl.o" lastModified="162cdc84160"/>
         <source file="../../../objs/linux/atanormapss.o" lastModified="162cdc38288"/>
         <source file="../../../objs/linux/atanormapu.o" lastModified="162cdc39228"/>
         <source file="../../../objs/linux/atanormapuf.o" lastModified="162cdc39de0"/>
         <source file="../../../objs/linux/atanormapui.o" lastModified="162cdc3ad80"/>
         <source file="../../../objs/linux/atanormapul.o" lastModified="162cdc85100"/>
         <source file="../../../objs/linux/atanormapuu.o" lastModified="162cdc3b938"/>
         <source file="../../../objs/linux/atanorprimemap.o" lastModified="162cdc3c8d8"/>
         <source file="../../../objs/linux/atanorprimemapf.o" lastModified="162cdc3d878"/>
         <source file="../../../objs/linux/atanorprimemapff.o" lastModified="162cdc3e430"/>
         <source file="../../../objs/linux/atanorprimemapfi.o" lastModified="162cdc3f3d0"/>
         <source file="../../../objs/linux/atanorprimemapfl.o" lastModified="162cdc860a0"/>
         <source file="../../../objs/linux/atanorprimemapfs.o" lastModified="162cdc3ff88"/>
         <source file="../../../objs/linux/atanorprimemapfu.o" lastModified="162cdc40f28"/>
         <source file="../../../objs/linux/atanorprimemapi.o" lastModified="162cdc41ae0"/>
         <source file="../../../objs/linux/atanorprimemapif.o" lastModified="162cdc42698"/>
         <source file="../../../objs/linux/atanorprimemapii.o" lastModified="162cdc43638"/>
         <source file="../../../objs/linux/atanorprimemapis.o" lastModified="162cdc441f0"/>
         <source file="../../../objs/linux/atanorprimemapiu.o" lastModified="162cdc45190"/>
         <source file="../../../objs/linux/atanorprimemapl.o" lastModified="162cdc86c58"/>
         <source file="../../../objs/linux/atanorprimemaplf.o" lastModified="162cdc87bf8"/>
         <source file="../../../objs/linux/atanorprimemapll.o" lastModified="162cdc887b0"/>
         <source file="../../../objs/linux/atanorprimemapls.o" lastModified="162cdc89750"/>
         <source file="../../../objs/linux/atanorprimemaplu.o" lastModified="162cdc8a6f0"/>
         <source file="../../../objs/linux/atanorprimemapsf.o" lastModified="162cdc46130"/>
         <source file="../../../objs/linux/atanorprimemapsi.o" lastModified="162cdc470d0"/>
         <source file="../../../objs/linux/atanorprimemapsl.o" lastModified="162cdc8b690"/>
         <source file="../../../objs/linux/atanorprimemapss.o" lastModified="162cdc47c88"/>
         <source file="../../../objs/linux/atanorprimemapu.o" lastModified="162cdc49010"/>
         <source file="../../../objs/linux/atanorprimemapuf.o" lastModified="162cdc49fb0"/>
         <source file="../../../objs/linux/atanorprimemapui.o" lastModified="162cdc4af50"/>
         <source file="../../../objs/linux/atanorprimemapul.o" lastModified="162cdc8c630"/>
         <source file="../../../objs/linux/atanorprimemapuu.o" lastModified="162cdc4bef0"/>
         <source file="../../../objs/linux/atanorrawstring.o" lastModified="162cdc72438"/>
         <source file="../../../objs/linux/atanorshort.o" lastModified="162cdc4c6c0"/>
         <source file="../../../objs/linux/atanorsocket.o" lastModified="162cdc4d278"/>
         <source file="../../../objs/linux/atanorstdin.o" lastModified="162cdc4da48"/>
         <source file="../../../objs/linux/atanorstring.o" lastModified="162cdc50158"/>
         <source file="../../../objs/linux/atanorsvector.o" lastModified="162cdc514e0"/>
         <source file="../../../objs/linux/atanorsynode.o" lastModified="162cdc23680"/>
         <source file="../../../objs/linux/atanorsys.o" lastModified="162cdc52098"/>
         <source file="../../../objs/linux/atanortable.o" lastModified="162cdc24a08"/>
         <source file="../../../objs/linux/atanortime.o" lastModified="162cdc52868"/>
         <source file="../../../objs/linux/atanortransducer.o" lastModified="162cdc53808"/>
         <source file="../../../objs/linux/atanortreemap.o" lastModified="162cdc547a8"/>
         <source file="../../../objs/linux/atanortreemapf.o" lastModified="162cdc55360"/>
         <source file="../../../objs/linux/atanortreemapff.o" lastModified="162cdc55f18"/>
         <source file="../../../objs/linux/atanortreemapfi.o" lastModified="162cdc56eb8"/>
         <source file="../../../objs/linux/atanortreemapfl.o" lastModified="162cdc8d5d0"/>
         <source file="../../../objs/linux/atanortreemapfs.o" lastModified="162cdc57a70"/>
         <source file="../../../objs/linux/atanortreemapfu.o" lastModified="162cdc58a10"/>
         <source file="../../../objs/linux/atanortreemapi.o" lastModified="162cdc595c8"/>
         <source file="../../../objs/linux/atanortreemapif.o" lastModified="162cdc5a180"/>
         <source file="../../../objs/linux/atanortreemapii.o" lastModified="162cdc5ad38"/>
         <source file="../../../objs/linux/atanortreemapis.o" lastModified="162cdc5bcd8"/>
         <source file="../../../objs/linux/atanortreemapiu.o" lastModified="162cdc5c890"/>
         <source file="../../../objs/linux/atanortreemapl.o" lastModified="162cdc8e570"/>
         <source file="../../../objs/linux/atanortreemaplf.o" lastModified="162cdc8f128"/>
         <source file="../../../objs/linux/atanortreemapll.o" lastModified="162cdc900c8"/>
         <source file="../../../objs/linux/atanortreemapls.o" lastModified="162cdc90c80"/>
         <source file="../../../objs/linux/atanortreemaplu.o" lastModified="162cdc91c20"/>
         <source file="../../../objs/linux/atanortreemapsf.o" lastModified="162cdc5d830"/>
         <source file="../../../objs/linux/atanortreemapsi.o" lastModified="162cdc5e3e8"/>
         <source file="../../../objs/linux/atanortreemapsl.o" lastModified="162cdc92bc0"/>
         <source file="../../../objs/linux/atanortreemapss.o" lastModified="162cdc5efa0"/>
         <source file="../../../objs/linux/atanortreemapu.o" lastModified="162cdc5ff40"/>
         <source file="../../../objs/linux/atanortreemapuf.o" lastModified="162cdc60af8"/>
         <source file="../../../objs/linux/atanortreemapui.o" lastModified="162cdc61a98"/>
         <source file="../../../objs/linux/atanortreemapul.o" lastModified="162cdc93778"/>
         <source file="../../../objs/linux/atanortreemapuu.o" lastModified="162cdc62a38"/>
         <source file="../../../objs/linux/atanorufile.o" lastModified="162cdc19270"/>
         <source file="../../../objs/linux/atanorustring.o" lastModified="162cdc64d60"/>
         <source file="../../../objs/linux/atanoruvector.o" lastModified="162cdc660e8"/>
         <source file="../../../objs/linux/atanorvector.o" lastModified="162cdc67858"/>
         <source file="../../../objs/linux/automate.o" lastModified="162cdc68028"/>
         <source file="../../../objs/linux/automaton.o" lastModified="162cdc68be0"/>
         <source file="../../../objs/linux/codecompile.o" lastModified="162cdc6bea8"/>
         <source file="../../../objs/linux/codeexecute.o" lastModified="162cdc6da00"/>
         <source file="../../../objs/linux/codeoperations.o" lastModified="162cdc70110"/>
         <source file="../../../objs/linux/codeparse.o" lastModified="162cdc6f558"/>
         <source file="../../../objs/linux/containerrecording.o" lastModified="162cdc73ba8"/>
         <source file="../../../objs/linux/conversion.o" lastModified="162cdc75318"/>
         <source file="../../../objs/linux/globalatanor.o" lastModified="162cdc75ae8"/>
         <source file="../../../objs/linux/objectrecording.o" lastModified="162cdc76a88"/>
         <source file="../../../objs/linux/predicate.o" lastModified="162cdc789c8"/>
         <source file="../../../objs/linux/predicatefunctions.o" lastModified="162cdc79968"/>
         <source file="../../../objs/linux/procedures.o" lastModified="162cdc7b4c0"/>
         <source file="../../../objs/linux/tools.o" lastModified="162cdc7c460"/>
         <source file="../../objs/linux/jatanor.o" lastModified="162cdd27a90"/>
      </target>
   </processor>
</history>
